README.rst
setup.py
xframes/__init__.py
xframes/aggregate.py
xframes/aggregator_impl.py
xframes/aggregator_property_set.py
xframes/cmp_rows.py
xframes/default.ini
xframes/dsq.py
xframes/environment.py
xframes/fileio.py
xframes/frequent.py
xframes/heapdict.py
xframes/lineage.py
xframes/object_utils.py
xframes/perf_tracker.py
xframes/prettytable.py
xframes/singleton.py
xframes/sketch.py
xframes/sketch_impl.py
xframes/spark_context.py
xframes/traced_object.py
xframes/type_utils.py
xframes/utils.py
xframes/version.py
xframes/xarray.py
xframes/xarray_impl.py
xframes/xframe.py
xframes/xframe_impl.py
xframes/xplot.py
xframes/xrdd.py
xframes/xstream.py
xframes/xstream_impl.py
xframes.egg-info/PKG-INFO
xframes.egg-info/SOURCES.txt
xframes.egg-info/dependency_links.txt
xframes.egg-info/requires.txt
xframes.egg-info/top_level.txt
xframes/conf/log4j.properties
xframes/conf/log4j.properties.template
xframes/conf/spark-defaults.conf.template
xframes/conf/spark-env.sh.template
xframes/deps/__init__.py
xframes/deps/matplotlib_mock.py
xframes/deps/numpy_mock.py
xframes/deps/pandas_mock.py
xframes/deps/py4j_mock.py
xframes/toolkit/__init__.py
xframes/toolkit/classify.py
xframes/toolkit/cluster.py
xframes/toolkit/model.py
xframes/toolkit/recommend.py
xframes/toolkit/regression.py
xframes/toolkit/text.py