Metadata-Version: 1.1
Name: xframes
Version: 0.3.7
Summary: XFrame data manipulation for Spark.
Home-page: https://github.com/cchayden/xframes.git
Author: Charles Hayden
Author-email: cchayden@gmail.com
License: Apache Software License 2.0
Platform: any
Classifier: Programming Language :: Python
Classifier: Development Status :: 4 - Beta
Classifier: Natural Language :: English
Classifier: Environment :: Console
Classifier: Intended Audience :: Developers
Classifier: License :: OSI Approved :: Apache Software License
Classifier: Operating System :: OS Independent
Classifier: Topic :: Software Development :: Libraries :: Python Modules
Provides: xframes
